nonebot_plugin_h2e/__init__.py
nonebot_plugin_h2e/h2e_info.py
nonebot_plugin_h2e/h2e_sports_type.py
nonebot_plugin_h2e/h2e_tool.py
nonebot_plugin_h2e/resource/fitness/withEquipment_BackM.json
nonebot_plugin_h2e/resource/fitness/withEquipment_HipM.json
nonebot_plugin_h2e/resource/fitness/withEquipment_LegM.json
nonebot_plugin_h2e/resource/fitness/withEquipment_ShoulderM.json
nonebot_plugin_h2e/resource/fitness/withEquipment_TrA.json
nonebot_plugin_h2e/resource/fitness/withEquipment_WaistM.json
nonebot_plugin_h2e/resource/fitness/withoutEquipment_BackM.json
nonebot_plugin_h2e/resource/fitness/withoutEquipment_HipM.json
nonebot_plugin_h2e/resource/fitness/withoutEquipment_LegM.json
nonebot_plugin_h2e/resource/fitness/withoutEquipment_ShoulderM.json
nonebot_plugin_h2e/resource/fitness/withoutEquipment_TrA.json
nonebot_plugin_h2e/resource/fitness/withoutEquipment_WaistM.json
nonebot_plugin_h2e/resource/swim/1.json
nonebot_plugin_h2e/resource/swim/2.json
nonebot_plugin_h2e/resource/swim/3.json
nonebot_plugin_h2e/resource/swim/4.json
nonebot_plugin_h2e/resource/swim/withEquipment_BackM.json
nonebot_plugin_h2e/resource/swim/withEquipment_HipM.json
nonebot_plugin_h2e/resource/swim/withEquipment_LegM.json
nonebot_plugin_h2e/resource/swim/withEquipment_ShoulderM.json
nonebot_plugin_h2e/resource/swim/withEquipment_TrA.json
nonebot_plugin_h2e/resource/swim/withEquipment_WaistM.json
nonebot_plugin_h2e/resource/swim/withoutEquipment_BackM.json
nonebot_plugin_h2e/resource/swim/withoutEquipment_HipM.json
nonebot_plugin_h2e/resource/swim/withoutEquipment_LegM.json
nonebot_plugin_h2e/resource/swim/withoutEquipment_ShoulderM.json
nonebot_plugin_h2e/resource/swim/withoutEquipment_TrA.json
nonebot_plugin_h2e/resource/swim/withoutEquipment_WaistM.json
nonebot_plugin_h2e/resource/yoga/withEquipment_BackM.json
nonebot_plugin_h2e/resource/yoga/withEquipment_HipM.json
nonebot_plugin_h2e/resource/yoga/withEquipment_LegM.json
nonebot_plugin_h2e/resource/yoga/withEquipment_ShoulderM.json
nonebot_plugin_h2e-0.1.3.dist-info/LICENSE
nonebot_plugin_h2e-0.1.3.dist-info/METADATA
nonebot_plugin_h2e-0.1.3.dist-info/WHEEL
nonebot_plugin_h2e-0.1.3.dist-info/RECORD
